<?xml version="1.0" standalone="yes"?>
<JFormDataSet xmlns="http://tempuri.org/JFormDataSet.xsd">
  <type>
    <type>list</type>
    <size>1</size>
    <validate>options</validate>
  </type>
  <type>
    <type>textarea</type>
    <rows>3</rows>
    <cols>30</cols>
  </type>
  <type>
    <type>text</type>
    <filter>string</filter>
    <size>30</size>
  </type>
  <type>
    <type>checkbox</type>
  </type>
  <type>
    <type>checkboxes</type>
  </type>
  <type>
    <type>category</type>
    <extension>com_content</extension>
  </type>
  <type>
    <type>calendar</type>
    <format>%Y-%m-%d %H:%M:%S</format>
    <filter>user_utc</filter>
    <size>22</size>
  </type>
  <type>
    <type>imagelist</type>
  </type>
  <type>
    <type>editor</type>
    <buttons>true</buttons>
  </type>
  <type>
    <type>email</type>
    <filter>string</filter>
    <size>30</size>
    <validate>email</validate>
  </type>
  <type>
    <type>radio</type>
  </type>
  <type>
  	<type>sql</type>
  </type>
  <type>
  	<type>modulelayout</type>
  </type>
  <type>
  	<type>media</type>
  </type>
  <type>
  	<type>hidden</type>
  </type>
  <type>
  	<type>spacer</type>
  </type>
  <type>
  	<type>contentlanguage</type>
  </type>
  <type>
  	<type>accesslevel</type>
  </type>
  <type>
    <type>column</type>
  </type>
  <type>
    <type>rules</type>
  </type>
</JFormDataSet>